forest/__init__.py
forest/_config.py
forest/base.py
forest/setup.py
forest/_build_utils/__init__.py
forest/_build_utils/min_dependencies.py
forest/_build_utils/openmp_helpers.py
forest/_build_utils/pre_build_helpers.py
forest/ensemble/Accuracy_lvig.py
forest/ensemble/ExtraTreeRegressor.py
forest/ensemble/RFRegressor.py
forest/ensemble/XGBoost.py
forest/ensemble/__init__.py
forest/ensemble/_forest.py
forest/tree/__init__.py
forest/tree/_classes.py
forest/tree/_tree.cp38-win32.pyd
forest/tree/_tree.pxd
forest/tree/_utils.cp38-win32.pyd
forest/tree/_utils.pxd
forest/tree/setup.py
forest_gis-2.0.0.dist-info/METADATA
forest_gis-2.0.0.dist-info/WHEEL
forest_gis-2.0.0.dist-info/top_level.txt
forest_gis-2.0.0.dist-info/RECORD
