Metadata-Version: 2.1
Name: forest-gis
Version: 2.0.0
Summary: A set of python modules for machine learning and data mining
Home-page: https://github.com/PowderL/forest-gis
Maintainer: Tao Li
Maintainer-email: lp1559345469@gmail.com
License: new BSD
Download-URL: https://pypi.org/project/forest-gis/#files
Project-URL: Bug Tracker, https://github.com/PowderL/forest-gis
Project-URL: Source Code, https://github.com/PowderL/forest-gis
Platform: UNKNOWN
Classifier: Intended Audience :: Science/Research
Classifier: Intended Audience :: Developers
Classifier: License :: OSI Approved
Classifier: Programming Language :: C
Classifier: Programming Language :: Python
Classifier: Topic :: Software Development
Classifier: Topic :: Scientific/Engineering
Classifier: Operating System :: Microsoft :: Windows
Classifier: Operating System :: POSIX
Classifier: Operating System :: Unix
Classifier: Operating System :: MacOS
Classifier: Programming Language :: Python :: 3
Classifier: Programming Language :: Python :: 3.6
Classifier: Programming Language :: Python :: 3.7
Classifier: Programming Language :: Python :: 3.8
Classifier: Programming Language :: Python :: Implementation :: CPython
Classifier: Programming Language :: Python :: Implementation :: PyPy
Requires-Python: >=3.6
